db/aes_sbox_stream_cipher.sv
module aes_sbox_stream_cipher (
   input            clk
  ,input            rst_n	  // reset signal, active low
  ,input            din_valid     //1'b1 used to notify input character validity, normally 1'b0
  ,input      [7:0] simmetric_key
  ,input      [7:0] txt_in_char
  ,output reg [7:0] txt_out_char
  ,output reg [0:0] dout_ready	  //1'b1 used to notify input character validity, normally 1'b0
);

  // ---------------------------------------------------------------------------
  // State Variables
  // ---------------------------------------------------------------------------

  localparam S0 = 2'b00;
  localparam S1_INIT = 2'b01;
  localparam S1 = 2'b11;
  localparam S2 = 2'b10;

  // ---------------------------------------------------------------------------
  // look-up table aes-sbox
  // ---------------------------------------------------------------------------

  function bit [7:0] sbox_lut;
  		input [7:0] lut_in;
  		case (lut_in)
  			8'h00: sbox_lut = 8'h63;
  			8'h01: sbox_lut = 8'h7c;
  			8'h02: sbox_lut = 8'h77;
  			8'h03: sbox_lut = 8'h7b;
  			8'h04: sbox_lut = 8'hf2;
  			8'h05: sbox_lut = 8'h6b;
  			8'h06: sbox_lut = 8'h6f;
  			8'h07: sbox_lut = 8'hc5;
  			8'h08: sbox_lut = 8'h30;
  			8'h09: sbox_lut = 8'h01;
  			8'h0a: sbox_lut = 8'h67;
  			8'h0b: sbox_lut = 8'h2b;
  			8'h0c: sbox_lut = 8'hfe;
  			8'h0d: sbox_lut = 8'hd7;
  			8'h0e: sbox_lut = 8'hab;
  			8'h0f: sbox_lut = 8'h76;
  			8'h10: sbox_lut = 8'hca;
  			8'h11: sbox_lut = 8'h82;
  			8'h12: sbox_lut = 8'hc9;
  			8'h13: sbox_lut = 8'h7d;
  			8'h14: sbox_lut = 8'hfa;
  			8'h15: sbox_lut = 8'h59;
  			8'h16: sbox_lut = 8'h47;
  			8'h17: sbox_lut = 8'hf0;
  			8'h18: sbox_lut = 8'had;
  			8'h19: sbox_lut = 8'hd4;
  			8'h1a: sbox_lut = 8'ha2;
  			8'h1b: sbox_lut = 8'haf;
  			8'h1c: sbox_lut = 8'h9c;
  			8'h1d: sbox_lut = 8'ha4;
  			8'h1e: sbox_lut = 8'h72;
  			8'h1f: sbox_lut = 8'hc0;
  			8'h20: sbox_lut = 8'hb7;
  			8'h21: sbox_lut = 8'hfd;
  			8'h22: sbox_lut = 8'h93;
  			8'h23: sbox_lut = 8'h26;
  			8'h24: sbox_lut = 8'h36;
  			8'h25: sbox_lut = 8'h3f;
  			8'h26: sbox_lut = 8'hf7;
  			8'h27: sbox_lut = 8'hcc;
  			8'h28: sbox_lut = 8'h34;
  			8'h29: sbox_lut = 8'ha5;
  			8'h2a: sbox_lut = 8'he5;
  			8'h2b: sbox_lut = 8'hf1;
  			8'h2c: sbox_lut = 8'h71;
  			8'h2d: sbox_lut = 8'hd8;
  			8'h2e: sbox_lut = 8'h31;
  			8'h2f: sbox_lut = 8'h15;
  			8'h30: sbox_lut = 8'h04;
  			8'h31: sbox_lut = 8'hc7;
  			8'h32: sbox_lut = 8'h23;
  			8'h33: sbox_lut = 8'hc3;
  			8'h34: sbox_lut = 8'h18;
  			8'h35: sbox_lut = 8'h96;
  			8'h36: sbox_lut = 8'h05;
  			8'h37: sbox_lut = 8'h9a;
  			8'h38: sbox_lut = 8'h07;
  			8'h39: sbox_lut = 8'h12;
  			8'h3a: sbox_lut = 8'h80;
  			8'h3b: sbox_lut = 8'he2;
  			8'h3c: sbox_lut = 8'heb;
  			8'h3d: sbox_lut = 8'h27;
  			8'h3e: sbox_lut = 8'hb2;
  			8'h3f: sbox_lut = 8'h75;
  			8'h40: sbox_lut = 8'h09;
  			8'h41: sbox_lut = 8'h83;
  			8'h42: sbox_lut = 8'h2c;
  			8'h43: sbox_lut = 8'h1a;
  			8'h44: sbox_lut = 8'h1b;
  			8'h45: sbox_lut = 8'h6e;
  			8'h46: sbox_lut = 8'h5a;
  			8'h47: sbox_lut = 8'ha0;
  			8'h48: sbox_lut = 8'h52;
  			8'h49: sbox_lut = 8'h3b;
  			8'h4a: sbox_lut = 8'hd6;
  			8'h4b: sbox_lut = 8'hb3;
  			8'h4c: sbox_lut = 8'h29;
  			8'h4d: sbox_lut = 8'he3;
  			8'h4e: sbox_lut = 8'h2f;
  			8'h4f: sbox_lut = 8'h84;
  			8'h50: sbox_lut = 8'h53;
  			8'h51: sbox_lut = 8'hd1;
  			8'h52: sbox_lut = 8'h00;
  			8'h53: sbox_lut = 8'hed;
  			8'h54: sbox_lut = 8'h20;
  			8'h55: sbox_lut = 8'hfc;
  			8'h56: sbox_lut = 8'hb1;
  			8'h57: sbox_lut = 8'h5b;
  			8'h58: sbox_lut = 8'h6a;
  			8'h59: sbox_lut = 8'hcb;
  			8'h5a: sbox_lut = 8'hbe;
  			8'h5b: sbox_lut = 8'h39;
  			8'h5c: sbox_lut = 8'h4a;
  			8'h5d: sbox_lut = 8'h4c;
  			8'h5e: sbox_lut = 8'h58;
  			8'h5f: sbox_lut = 8'hcf;
  			8'h60: sbox_lut = 8'hd0;
  			8'h61: sbox_lut = 8'hef;
  			8'h62: sbox_lut = 8'haa;
  			8'h63: sbox_lut = 8'hfb;
  			8'h64: sbox_lut = 8'h43;
  			8'h65: sbox_lut = 8'h4d;
  			8'h66: sbox_lut = 8'h33;
  			8'h67: sbox_lut = 8'h85;
  			8'h68: sbox_lut = 8'h45;
  			8'h69: sbox_lut = 8'hf9;
  			8'h6a: sbox_lut = 8'h02;
  			8'h6b: sbox_lut = 8'h7f;
  			8'h6c: sbox_lut = 8'h50;
  			8'h6d: sbox_lut = 8'h3c;
  			8'h6e: sbox_lut = 8'h9f;
  			8'h6f: sbox_lut = 8'ha8;
  			8'h70: sbox_lut = 8'h51;
  			8'h71: sbox_lut = 8'ha3;
  			8'h72: sbox_lut = 8'h40;
  			8'h73: sbox_lut = 8'h8f;
  			8'h74: sbox_lut = 8'h92;
  			8'h75: sbox_lut = 8'h9d;
  			8'h76: sbox_lut = 8'h38;
  			8'h77: sbox_lut = 8'hf5;
  			8'h78: sbox_lut = 8'hbc;
  			8'h79: sbox_lut = 8'hb6;
  			8'h7a: sbox_lut = 8'hda;
  			8'h7b: sbox_lut = 8'h21;
  			8'h7c: sbox_lut = 8'h10;
  			8'h7d: sbox_lut = 8'hff;
  			8'h7e: sbox_lut = 8'hf3;
  			8'h7f: sbox_lut = 8'hd2;
  			8'h80: sbox_lut = 8'hcd;
  			8'h81: sbox_lut = 8'h0c;
  			8'h82: sbox_lut = 8'h13;
  			8'h83: sbox_lut = 8'hec;
  			8'h84: sbox_lut = 8'h5f;
  			8'h85: sbox_lut = 8'h97;
  			8'h86: sbox_lut = 8'h44;
  			8'h87: sbox_lut = 8'h17;
  			8'h88: sbox_lut = 8'hc4;
  			8'h89: sbox_lut = 8'ha7;
  			8'h8a: sbox_lut = 8'h7e;
  			8'h8b: sbox_lut = 8'h3d;
  			8'h8c: sbox_lut = 8'h64;
  			8'h8d: sbox_lut = 8'h5d;
  			8'h8e: sbox_lut = 8'h19;
  			8'h8f: sbox_lut = 8'h73;
  			8'h90: sbox_lut = 8'h60;
  			8'h91: sbox_lut = 8'h81;
  			8'h92: sbox_lut = 8'h4f;
  			8'h93: sbox_lut = 8'hdc;
  			8'h94: sbox_lut = 8'h22;
  			8'h95: sbox_lut = 8'h2a;
  			8'h96: sbox_lut = 8'h90;
  			8'h97: sbox_lut = 8'h88;
  			8'h98: sbox_lut = 8'h46;
  			8'h99: sbox_lut = 8'hee;
  			8'h9a: sbox_lut = 8'hb8;
  			8'h9b: sbox_lut = 8'h14;
  			8'h9c: sbox_lut = 8'hde;
  			8'h9d: sbox_lut = 8'h5e;
  			8'h9e: sbox_lut = 8'h0b;
  			8'h9f: sbox_lut = 8'hdb;
  			8'ha0: sbox_lut = 8'he0;
  			8'ha1: sbox_lut = 8'h32;
  			8'ha2: sbox_lut = 8'h3a;
  			8'ha3: sbox_lut = 8'h0a;
  			8'ha4: sbox_lut = 8'h49;
  			8'ha5: sbox_lut = 8'h06;
  			8'ha6: sbox_lut = 8'h24;
  			8'ha7: sbox_lut = 8'h5c;
  			8'ha8: sbox_lut = 8'hc2;
  			8'ha9: sbox_lut = 8'hd3;
  			8'haa: sbox_lut = 8'hac;
  			8'hab: sbox_lut = 8'h62;
  			8'hac: sbox_lut = 8'h91;
  			8'had: sbox_lut = 8'h95;
  			8'hae: sbox_lut = 8'he4;
  			8'haf: sbox_lut = 8'h79;
  			8'hb0: sbox_lut = 8'he7;
  			8'hb1: sbox_lut = 8'hc8;
  			8'hb2: sbox_lut = 8'h37;
  			8'hb3: sbox_lut = 8'h6d;
  			8'hb4: sbox_lut = 8'h8d;
  			8'hb5: sbox_lut = 8'hd5;
  			8'hb6: sbox_lut = 8'h4e;
  			8'hb7: sbox_lut = 8'ha9;
  			8'hb8: sbox_lut = 8'h6c;
  			8'hb9: sbox_lut = 8'h56;
  			8'hba: sbox_lut = 8'hf4;
  			8'hbb: sbox_lut = 8'hea;
  			8'hbc: sbox_lut = 8'h65;
  			8'hbd: sbox_lut = 8'h7a;
  			8'hbe: sbox_lut = 8'hae;
  			8'hbf: sbox_lut = 8'h08;
  			8'hc0: sbox_lut = 8'hba;
  			8'hc1: sbox_lut = 8'h78;
  			8'hc2: sbox_lut = 8'h25;
  			8'hc3: sbox_lut = 8'h2e;
  			8'hc4: sbox_lut = 8'h1c;
  			8'hc5: sbox_lut = 8'ha6;
  			8'hc6: sbox_lut = 8'hb4;
  			8'hc7: sbox_lut = 8'hc6;
  			8'hc8: sbox_lut = 8'he8;
  			8'hc9: sbox_lut = 8'hdd;
  			8'hca: sbox_lut = 8'h74;
  			8'hcb: sbox_lut = 8'h1f;
  			8'hcc: sbox_lut = 8'h4b;
  			8'hcd: sbox_lut = 8'hbd;
  			8'hce: sbox_lut = 8'h8b;
  			8'hcf: sbox_lut = 8'h8a;
  			8'hd0: sbox_lut = 8'h70;
  			8'hd1: sbox_lut = 8'h3e;
  			8'hd2: sbox_lut = 8'hb5;
  			8'hd3: sbox_lut = 8'h66;
  			8'hd4: sbox_lut = 8'h48;
  			8'hd5: sbox_lut = 8'h03;
  			8'hd6: sbox_lut = 8'hf6;
  			8'hd7: sbox_lut = 8'h0e;
  			8'hd8: sbox_lut = 8'h61;
  			8'hd9: sbox_lut = 8'h35;
  			8'hda: sbox_lut = 8'h57;
  			8'hdb: sbox_lut = 8'hb9;
  			8'hdc: sbox_lut = 8'h86;
  			8'hdd: sbox_lut = 8'hc1;
  			8'hde: sbox_lut = 8'h1d;
  			8'hdf: sbox_lut = 8'h9e;
  			8'he0: sbox_lut = 8'he1;
  			8'he1: sbox_lut = 8'hf8;
  			8'he2: sbox_lut = 8'h98;
  			8'he3: sbox_lut = 8'h11;
  			8'he4: sbox_lut = 8'h69;
  			8'he5: sbox_lut = 8'hd9;
  			8'he6: sbox_lut = 8'h8e;
  			8'he7: sbox_lut = 8'h94;
  			8'he8: sbox_lut = 8'h9b;
  			8'he9: sbox_lut = 8'h1e;
  			8'hea: sbox_lut = 8'h87;
  			8'heb: sbox_lut = 8'he9;
  			8'hec: sbox_lut = 8'hce;
  			8'hed: sbox_lut = 8'h55;
  			8'hee: sbox_lut = 8'h28;
  			8'hef: sbox_lut = 8'hdf;
  			8'hf0: sbox_lut = 8'h8c;
  			8'hf1: sbox_lut = 8'ha1;
  			8'hf2: sbox_lut = 8'h89;
  			8'hf3: sbox_lut = 8'h0d;
  			8'hf4: sbox_lut = 8'hbf;
  			8'hf5: sbox_lut = 8'he6;
  			8'hf6: sbox_lut = 8'h42;
  			8'hf7: sbox_lut = 8'h68;
  			8'hf8: sbox_lut = 8'h41;
  			8'hf9: sbox_lut = 8'h99;
  			8'hfa: sbox_lut = 8'h2d;
  			8'hfb: sbox_lut = 8'h0f;
  			8'hfc: sbox_lut = 8'hb0;
  			8'hfd: sbox_lut = 8'h54;
  			8'hfe: sbox_lut = 8'hbb;
  			8'hff: sbox_lut = 8'h16;
  		endcase
  endfunction

  // ---------------------------------------------------------------------------
  // Logic wires driving inner circuits
  // ---------------------------------------------------------------------------

  wire [7:0] txt_xor_in;
  // ---------------------------------------------------------------------------
  // Registers
  // ---------------------------------------------------------------------------

  reg [7:0] counter_out;  //key register
  reg [7:0] txt_in;
  reg [1:0] star;         //status register

  // ---------------------------------------------------------------------------
  // Logic Design
  // ---------------------------------------------------------------------------

  assign txt_xor_in = txt_in;
  always @ (posedge clk or negedge rst_n)
    if(!rst_n) begin
      dout_ready <= 1'b0;
      star <= S0;
      txt_in <= 8'h00;
      counter_out <= 8'h00;
      txt_out_char <= 8'h00;
    end
    else begin
      case(star)
          S0:
            begin
              star <= S1_INIT;
              dout_ready  <= 1'b0;
              txt_in <= 8'h00;
              counter_out <= 8'h00;
              txt_out_char <= 8'h00;
            end
          S1_INIT:
            begin
              star <= (din_valid == 1'b1) ? S2 : S1_INIT;
              dout_ready  <= 1'b0;
              txt_in <= (din_valid == 1'b1) ? txt_in_char : 8'h00;
              counter_out <= (din_valid == 1'b1) ? simmetric_key : 8'h00;
              txt_out_char <= txt_out_char; 
            end
          S1:
            begin
              star <= (din_valid == 1'b1) ? S2 : S1;
              dout_ready  <= 1'b0;
              txt_in <= (din_valid == 1'b1) ? txt_in_char : 8'h00;
              counter_out <=  counter_out;  
              txt_out_char <= txt_out_char; 
            end
          S2:
            begin
              star <= (din_valid == 1'b1) ? S2 : S1;
              dout_ready  <= 1'b1;
              txt_in <= (din_valid == 1'b1) ? txt_in_char : 8'h00;
              counter_out  <= counter_out + 8'h01;
              txt_out_char <= sbox_lut(counter_out) ^ txt_xor_in;
            end
      endcase // star

    end

endmodule

tb/stream_cipher_tb_dec.sv
// -----------------------------------------------------------------------------
// Testbench of AES Sbox based stream cipher module
// -----------------------------------------------------------------------------

// -----------------------------------------------------------------------------
// Testbench for file encryption
// -----------------------------------------------------------------------------
module stream_cipher_tb_enc;

  reg clk = 1'b0;
  always #5 clk = !clk;

  reg rst_n = 1'b0;
  event reset_deassertion;

  initial begin
    #12.8 rst_n = 1'b1;
    -> reset_deassertion;
  end

  reg 	     din_valid;
  reg  [7:0] symmetric_key;
  reg  [7:0] txt_in_char;
  wire [7:0] txt_out_char;
  wire       dout_ready;

  aes_sbox_stream_cipher DECIPHER (
     .clk                       (clk)
    ,.rst_n                     (rst_n)
    ,.din_valid                 (din_valid)
    ,.simmetric_key             (symmetric_key)
    ,.txt_in_char               (txt_in_char)
    ,.txt_out_char              (txt_out_char)
    ,.dout_ready                (dout_ready)
  );

 
  int FP_PTXT;
  int FP_CTXT;
  string char;
  reg [7:0] CTXT [$];
  reg [7:0] PTXT [$];

  initial begin
    @(reset_deassertion);

    @(posedge clk);
    FP_CTXT = $fopen("../db/test/enc3", "rb");
    $write("Decrypting file 'enc0' to 'dec0.txt' ...\n");
    
    while($fscanf(FP_CTXT, "%c", char) == 1) begin
      txt_in_char = int'(char);
      symmetric_key = 8'h12;

      #2 din_valid = int'(1);

      @(posedge clk);
      if(dout_ready) begin
        PTXT.push_back(txt_out_char);
        $display("%c", txt_out_char);
      end

    end

    din_valid = int'(0);    //no more input data to supply
    $fclose(FP_CTXT);

    while(dout_ready) begin //still 2 byte to sample
    	@(posedge clk);
		if(dout_ready) begin
			PTXT.push_back(txt_out_char);
			$display("%c", txt_out_char);
		end
    end

    FP_PTXT = $fopen("../db/test/dec3.txt", "w");
    foreach(PTXT[i])
    $fwrite(FP_PTXT, "%c", PTXT[i]);

    $fclose(FP_PTXT);

    $display("Decryption completed");

    $stop;
  end

endmodule
// -----------------------------------------------------------------------------

tb/dec_wave.vcd
$date
	Sat Jun 19 14:43:53 2021
$end
$version
	ModelSim Version 2020.1
$end
$timescale
	1ps
$end
$scope module stream_cipher_tb_enc $end
$var reg 1 ! clk $end
$var reg 1 " rst_n $end
$var reg 1 # din_valid $end
$var reg 8 $ txt_in_char [7:0] $end
$var reg 8 % symmetric_key [7:0] $end
$var wire 1 & txt_out_char [7] $end
$var wire 1 ' txt_out_char [6] $end
$var wire 1 ( txt_out_char [5] $end
$var wire 1 ) txt_out_char [4] $end
$var wire 1 * txt_out_char [3] $end
$var wire 1 + txt_out_char [2] $end
$var wire 1 , txt_out_char [1] $end
$var wire 1 - txt_out_char [0] $end
$var wire 1 . dout_ready $end
$scope module DECIPHER $end
$var reg 2 / star [1:0] $end
$var reg 8 0 txt_in [7:0] $end
$upscope $end
$upscope $end
$enddefinitions $end
#0
b0 !
b0 "
bx #
0.
bx $
bx %
b0 0
b0 /
0&
0'
0(
0)
0*
0+
0,
0-
b0 /
b0 0
0.
0&
0'
0(
0)
0*
0+
0,
0-
#5
b1 !
#10
b0 !
#13
b1 "
#15
b1 !
b10100001 $
b10010 %
b1 /
#17
b1 #
#20
b0 !
#25
b1 !
b11000 $
b10 /
b10100001 0
#30
b0 !
#35
b1 !
b10010110 $
b11000 0
1.
1'
1(
1*
#40
b0 !
#45
b1 !
b110101 $
b10010110 0
0*
1+
1-
#50
b0 !
#55
b1 !
b101000 $
b110101 0
1*
0-
#60
b0 !
#65
b1 !
b11010000 $
b101000 0
#70
b0 !
#75
b1 !
b11011010 $
b11010000 0
1,
1-
#80
b0 !
#85
b1 !
b10111011 $
b11011010 0
0'
0*
0+
0,
0-
#90
b0 !
#95
b1 !
b11010000 $
b10111011 0
1'
1)
1+
1,
1-
#100
b0 !
#105
b1 !
b11000011 $
b11010000 0
0)
1*
#110
b0 !
#115
b1 !
b11111000 $
b11000011 0
1)
0*
0+
0-
#120
b0 !
#125
b1 !
b10000101 $
b11111000 0
0)
1*
1+
0,
#130
b0 !
#135
b1 !
b1111000 $
b10000101 0
0*
#140
b0 !
#145
b1 !
b0 #
b1111000 0
0'
0+
1-
#150
b0 !
#155
b1 !
b11 /
b0 0
0(
1*
1,
0-
#160
b0 !
#165
b1 !
0.
#170
b0 !
#175
b1 !
